prombin.py
prombin-1.2.dist-info/LICENSE
prombin-1.2.dist-info/METADATA
prombin-1.2.dist-info/WHEEL
prombin-1.2.dist-info/entry_points.txt
prombin-1.2.dist-info/top_level.txt
prombin-1.2.dist-info/RECORD
